billiard/__init__.py
billiard/_ext.py
billiard/_win.py
billiard/common.py
billiard/compat.py
billiard/connection.py
billiard/context.py
billiard/einfo.py
billiard/exceptions.py
billiard/forkserver.py
billiard/heap.py
billiard/managers.py
billiard/pool.py
billiard/popen_fork.py
billiard/popen_forkserver.py
billiard/popen_spawn_posix.py
billiard/popen_spawn_win32.py
billiard/process.py
billiard/queues.py
billiard/reduction.py
billiard/resource_sharer.py
billiard/semaphore_tracker.py
billiard/sharedctypes.py
billiard/spawn.py
billiard/synchronize.py
billiard/util.py
billiard/dummy/__init__.py
billiard/dummy/connection.py
billiard-4.0.1.dist-info/LICENSE.txt
billiard-4.0.1.dist-info/METADATA
billiard-4.0.1.dist-info/WHEEL
billiard-4.0.1.dist-info/top_level.txt
billiard-4.0.1.dist-info/RECORD
