Metadata-Version: 2.1
Name: billiard
Version: 4.0.1
Summary: Python multiprocessing fork with improvements and bugfixes
Home-page: https://github.com/celery/billiard
Author: R Oudkerk / Python Software Foundation
Author-email: python-dev@python.org
Maintainer: Asif Saif Uddin
Maintainer-email: auvipy@gmail.com
License: BSD
Keywords: multiprocessing pool process
Classifier: Development Status :: 5 - Production/Stable
Classifier: Intended Audience :: Developers
Classifier: Programming Language :: Python
Classifier: Programming Language :: C
Classifier: Programming Language :: Python :: 3
Classifier: Programming Language :: Python :: 3.7
Classifier: Programming Language :: Python :: 3.8
Classifier: Programming Language :: Python :: 3.9
Classifier: Programming Language :: Python :: 3.10
Classifier: Programming Language :: Python :: Implementation :: CPython
Classifier: Programming Language :: Python :: Implementation :: PyPy
Classifier: Operating System :: Microsoft :: Windows
Classifier: Operating System :: POSIX
Classifier: License :: OSI Approved :: BSD License
Classifier: Topic :: Software Development :: Libraries :: Python Modules
Classifier: Topic :: System :: Distributed Computing
Requires-Python: >=3.7
License-File: LICENSE.txt
